odoo/addons/hr_expense_cancel_confirm/README.rst
odoo/addons/hr_expense_cancel_confirm/__init__.py
odoo/addons/hr_expense_cancel_confirm/__manifest__.py
odoo/addons/hr_expense_cancel_confirm/data/config_parameter.xml
odoo/addons/hr_expense_cancel_confirm/i18n/hr_expense_cancel_confirm.pot
odoo/addons/hr_expense_cancel_confirm/i18n/it.po
odoo/addons/hr_expense_cancel_confirm/model/__init__.py
odoo/addons/hr_expense_cancel_confirm/model/hr_expense.py
odoo/addons/hr_expense_cancel_confirm/readme/CONFIGURE.rst
odoo/addons/hr_expense_cancel_confirm/readme/CONTRIBUTORS.rst
odoo/addons/hr_expense_cancel_confirm/readme/DESCRIPTION.rst
odoo/addons/hr_expense_cancel_confirm/static/description/icon.png
odoo/addons/hr_expense_cancel_confirm/static/description/index.html
odoo/addons/hr_expense_cancel_confirm/tests/__init__.py
odoo/addons/hr_expense_cancel_confirm/tests/test_hr_expense_cancel_confirm.py
odoo/addons/hr_expense_cancel_confirm/wizard/__init__.py
odoo/addons/hr_expense_cancel_confirm/wizard/cancel_confirm.py
odoo_addon_hr_expense_cancel_confirm-15.0.1.0.0.4.dist-info/METADATA
odoo_addon_hr_expense_cancel_confirm-15.0.1.0.0.4.dist-info/WHEEL
odoo_addon_hr_expense_cancel_confirm-15.0.1.0.0.4.dist-info/top_level.txt
odoo_addon_hr_expense_cancel_confirm-15.0.1.0.0.4.dist-info/RECORD
